logg_it/__init__.py
logg_it/loggit_function.py
easy_py_logger-1.0.3.dist-info/LICENSE
easy_py_logger-1.0.3.dist-info/METADATA
easy_py_logger-1.0.3.dist-info/WHEEL
easy_py_logger-1.0.3.dist-info/top_level.txt
easy_py_logger-1.0.3.dist-info/RECORD
