Metadata-Version: 2.2
Name: easy-py-logger
Version: 1.0.3
Summary: A easy lightweight robust Python logger.
Home-page: https://github.com/brianvess/easy-py-logger
Author: Brian Vess
Author-email: brianvess@icloud.com
Classifier: Programming Language :: Python :: 3
Classifier: License :: OSI Approved :: MIT License
Classifier: Operating System :: OS Independent
Requires-Python: >=3.6
License-File: LICENSE
Dynamic: author
Dynamic: author-email
Dynamic: classifier
Dynamic: description
Dynamic: description-content-type
Dynamic: home-page
Dynamic: requires-python
Dynamic: summary
